Pulldata/__init__.py
Pulldata/myfunctions.py
Pulldata-1.1.1.dist-info/METADATA
Pulldata-1.1.1.dist-info/WHEEL
Pulldata-1.1.1.dist-info/top_level.txt
Pulldata-1.1.1.dist-info/RECORD
