Metadata-Version: 2.1
Name: Pulldata
Version: 1.1.1
Summary: My first Python library
Author: Me
License: MIT
Platform: UNKNOWN
